tedfulk_kb_pycrawler/__init__.py
tedfulk_kb_pycrawler/models.py
tedfulk_kb_pycrawler/scrape_it.py
tedfulk_kb_pycrawler-0.1.6.dist-info/METADATA
tedfulk_kb_pycrawler-0.1.6.dist-info/WHEEL
tedfulk_kb_pycrawler-0.1.6.dist-info/RECORD
