Metadata-Version: 2.1
Name: tedfulk_kb_pycrawler
Version: 0.1.6
Summary: 
Author: Ted Fulk
Author-email: teddyfulk@gmail.com
Requires-Python: >=3.11,<4.0
Classifier: Programming Language :: Python :: 3
Classifier: Programming Language :: Python :: 3.11
Classifier: Programming Language :: Python :: 3.12
Requires-Dist: asyncio (>=3.4.3,<4.0.0)
Requires-Dist: fpdf (>=1.7.2,<2.0.0)
Requires-Dist: playwright (>=1.40.0,<2.0.0)
Requires-Dist: pydantic (>=2.5.3,<3.0.0)
